{
  "generatedAt": "2026-07-07T18:58:17.698Z",
  "note": "Auto-built from public local RSS feeds by scripts/fetch-events.mjs (GitHub Action, ~every 30 min). Headlines belong to their sources.",
  "news": [
    {
      "title": "Know Before You Go: Concerts In The Park Returns This Saturday",
      "url": "https://www.hometownstation.com/santa-clarita-news/arts-and-entertainment/know-before-you-go-concerts-in-the-park-returns-this-saturday-600870",
      "published": "2026-07-07T17:34:29.000Z",
      "source": "KHTS"
    },
    {
      "title": "Santa Clarita Set To Be The Site Of Five Different Film Productions (7/9-7/12)",
      "url": "https://www.hometownstation.com/santa-clarita-news/arts-and-entertainment/santa-clarita-set-to-be-the-site-of-five-different-film-productions-7-9-7-12-600789",
      "published": "2026-07-07T16:23:23.000Z",
      "source": "KHTS"
    },
    {
      "title": "Why U.S. Lawmakers Are Targeting Sweepstakes Casinos In 2026",
      "url": "https://www.hometownstation.com/featured-stories/why-u-s-lawmakers-are-targeting-sweepstakes-casinos-in-2026-600860",
      "published": "2026-07-07T09:57:29.000Z",
      "source": "KHTS"
    },
    {
      "title": "Watch parties to continue as U.S. run comes to end",
      "url": "https://signalscv.com/2026/07/watch-parties-to-continue-as-u-s-run-comes-to-end/",
      "published": "2026-07-07T03:01:39.000Z",
      "source": "The Signal"
    },
    {
      "title": "Temps to rise through Friday",
      "url": "https://signalscv.com/2026/07/temps-to-rise-through-friday/",
      "published": "2026-07-07T02:41:55.000Z",
      "source": "The Signal"
    },
    {
      "title": "City announces night-time roadwork near mall",
      "url": "https://signalscv.com/2026/07/city-announces-night-time-roadwork-near-mall/",
      "published": "2026-07-07T01:27:54.000Z",
      "source": "The Signal"
    },
    {
      "title": "‘Martin’ Fire burns near I-5, Templin Highway",
      "url": "https://signalscv.com/2026/07/martin-fire-burns-near-i-5-templin-highway/",
      "published": "2026-07-06T23:55:00.000Z",
      "source": "The Signal"
    },
    {
      "title": "Martins Fire: Vehicle Fire Spreads To Brush Near Castaic, Evacuation Warning Issued",
      "url": "https://www.hometownstation.com/santa-clarita-news/scv-emergency/santa-clarita-fire/martin-fire-vehicle-fire-spreads-to-brush-near-castaic-600837",
      "published": "2026-07-06T23:37:01.000Z",
      "source": "KHTS"
    },
    {
      "title": "COC receives $1.1M donation from The Broad Foundation for ATC",
      "url": "https://signalscv.com/2026/07/coc-receives-1-1m-donation-from-the-broad-foundation-for-atc/",
      "published": "2026-07-06T23:30:44.000Z",
      "source": "The Signal"
    },
    {
      "title": "CHP: Man arrested on suspicion of DUI, possession of firearm",
      "url": "https://signalscv.com/2026/07/chp-man-arrested-on-suspicion-of-dui-possession-of-firearm/",
      "published": "2026-07-06T23:21:45.000Z",
      "source": "The Signal"
    },
    {
      "title": "Person trapped after traffic collision in Saugus",
      "url": "https://signalscv.com/2026/07/person-trapped-after-traffic-collision-in-saugus/",
      "published": "2026-07-06T23:18:03.000Z",
      "source": "The Signal"
    },
    {
      "title": "Hart alum selected for TV Academy internship",
      "url": "https://signalscv.com/2026/07/hart-alum-selected-for-tv-academy-internship/",
      "published": "2026-07-06T23:15:39.000Z",
      "source": "The Signal"
    },
    {
      "title": "Deputies: Man arrested on suspicion after assault in Canyon Country",
      "url": "https://signalscv.com/2026/07/deputies-man-arrested-on-suspicion-after-assault-in-canyon-country/",
      "published": "2026-07-06T23:13:20.000Z",
      "source": "The Signal"
    },
    {
      "title": "Planners to discuss city design standards",
      "url": "https://signalscv.com/2026/07/planners-to-discuss-city-design-standards/",
      "published": "2026-07-06T23:07:55.000Z",
      "source": "The Signal"
    },
    {
      "title": "The Broad Foundation Donates $1.1 Million Toward College Of The Canyons ATC",
      "url": "https://www.hometownstation.com/santa-clarita-news/education/college-of-the-canyons/the-broad-foundation-donates-1-1-million-toward-college-of-the-canyons-atc-600799",
      "published": "2026-07-06T21:30:38.000Z",
      "source": "KHTS"
    },
    {
      "title": "Naked Man Arrested After Defecating On Canyon Country Sidewalk",
      "url": "https://www.hometownstation.com/santa-clarita-news/crime/naked-man-arrested-after-defecating-on-canyon-country-sidewalk-600771",
      "published": "2026-07-06T20:38:16.000Z",
      "source": "KHTS"
    },
    {
      "title": "Panorama City Medical Center recognized for older adult care",
      "url": "https://signalscv.com/2026/07/panorama-city-medical-center-recognized-for-older-adult-care/",
      "published": "2026-07-06T19:39:46.000Z",
      "source": "The Signal"
    },
    {
      "title": "Cool Rewards For Positive Choices: LASD, 7-Eleven Bring ‘Operation Chill’ To L.A. County",
      "url": "https://www.hometownstation.com/santa-clarita-news/community-news/cool-rewards-for-positive-choices-lasd-7-eleven-bring-operation-chill-to-l-a-county-600780",
      "published": "2026-07-06T19:00:49.000Z",
      "source": "KHTS"
    },
    {
      "title": "Bill aimed at ‘elderly’ parole law moves on",
      "url": "https://signalscv.com/2026/07/bill-aimed-at-elderly-parole-law-moves-on/",
      "published": "2026-07-06T18:28:53.000Z",
      "source": "The Signal"
    },
    {
      "title": "CARB Approves $70 Million For Reduced Emissions Off-Road",
      "url": "https://www.hometownstation.com/santa-clarita-latest-news/carb-approves-70-million-for-reduced-emissions-off-road-600809",
      "published": "2026-07-06T17:51:15.000Z",
      "source": "KHTS"
    },
    {
      "title": "Santa Clarita Valley Sees 36 Arrests Over Fourth Of July Weekend, Including Child Luring, Shoplifting Cases",
      "url": "https://www.hometownstation.com/santa-clarita-news/crime/santa-clarita-valley-sees-36-arrests-over-fourth-of-july-weekend-including-child-luring-shoplifting-cases-600817",
      "published": "2026-07-06T17:30:27.000Z",
      "source": "KHTS"
    },
    {
      "title": "Golden Valley’s Miguel Mayorga ready to tackle expectations and goals",
      "url": "https://signalscv.com/2026/07/golden-valleys-miguel-mayorga-ready-to-tackle-expectations-and-goals/",
      "published": "2026-07-06T16:49:35.000Z",
      "source": "The Signal"
    },
    {
      "title": "Season-By-Season HVAC Maintenance For Homes In Stilwell, OK",
      "url": "https://www.hometownstation.com/featured-stories/season-by-season-hvac-maintenance-for-homes-in-stilwell-ok-600731",
      "published": "2026-07-06T16:44:36.000Z",
      "source": "KHTS"
    },
    {
      "title": "Celebrating America’s semiquincentennial birthday, Santa Clarita-style",
      "url": "https://signalscv.com/2026/07/celebrating-americas-semiquincentennial-birthday-santa-clarita-style/",
      "published": "2026-07-05T16:50:02.000Z",
      "source": "The Signal"
    }
  ]
}
